{
  "AmmunitionId": null,
  "Availability": 1,
  "CellType": "1",
  "Color": "#00000000",
  "ComponentStatsId": 261,
  "Description": "",
  "DeviceId": null,
  "DisplayCategory": 2,
  "DroneBayId": null,
  "DroneId": null,
  "Faction": 16,
  "Icon": "armor62",
  "Id": 261,
  "ItemType": 1,
  "Layout": "1111",
  "Level": 25,
  "Name": "$BionicArmor_M",
  "PossibleModifications": [
    3,
    1
  ],
  "Restrictions": {
    "ComponentGroupTag": null,
    "MaxComponentAmount": 0,
    "NotForMechanicShips": false,
    "NotForOrganicShips": false,
    "ShipSizes": [],
    "UniqueComponentTag": ""
  },
  "WeaponId": null,
  "WeaponSlotType": ""
}